<?xml version="1.0" encoding="UTF-8"?>
<page id="1253" page_number="1" label="1" previous="1252.xml" next="1254.xml">
  <entry id="35492" type="1" text="1. EMPERO acerca de los tiempos y de los momentos, no tenéis, hermanos, necesidad de que yo os escriba:"/>
  <entry id="35493" type="1" text="2. Porque vosotros sabéis bien, que el día del Señor vendrá así como ladrón de noche,"/>
  <entry id="35494" type="1" text="3. Que cuando dirán, Paz y seguridad, entonces vendrá sobre ellos destrucción de repente, como los dolores a la mujer preñada; y no escaparán."/>
  <entry id="35495" type="1" text="4. Mas vosotros, hermanos, no estáis en tinieblas, para que aquel día os sobrecoja como ladrón;"/>
  <entry id="35496" type="1" text="5. Porque todos vosotros sois hijos de luz, é hijos del día; no somos de la noche, ni de las tinieblas."/>
  <entry id="35497" type="1" text="6. Por tanto, no durmamos como los demás; antes velemos y seamos sobrios."/>
  <entry id="35498" type="1" text="7. Porque los que duermen, de noche duermen; y los que están borrachos, de noche están borrachos."/>
  <entry id="35499" type="1" text="8. Mas nosotros, que somos del día, estemos sobrios, vestidos de cota de fe y de caridad, y la esperanza de salud por yelmo."/>
  <entry id="35500" type="1" text="9. Porque no nos ha puesto Dios para ira, sino para alcanzar salud por nuestro Señor Jesucristo;"/>
  <entry id="35501" type="1" text="10. El cual murió por nosotros, para que ó que velemos, ó que durmamos, vivamos juntamente con él."/>
  <entry id="35502" type="1" text="11. Por lo cual, consolaos los unos a los otros, y edificaos los unos a los otros, así como lo hacéis."/>
  <entry id="35503" type="1" style="subtitulo" text="Pablo exhorta a los hermanos"/>
  <entry id="35504" type="1" text="12. Y os rogamos, hermanos, que reconozcáis a los que trabajan entre vosotros, y os presiden en el Señor, y os amonestan:"/>
  <entry id="35505" type="1" text="13. Y que los tengáis en mucha estima por amor de su obra. Tened paz los unos con los otros."/>
  <entry id="35506" type="1" text="14. También os rogamos, hermanos, que amonestéis a los que andan desordenadamente, que consoléis a los de poco ánimo, que soportéis a los flacos, que seáis sufridos para con todos."/>
  <entry id="35507" type="1" text="15. Mirad que ninguno dé a otro mal por mal; antes seguid lo bueno siempre los unos para con los otros, y para con todos."/>
  <entry id="35508" type="1" text="16. Estad siempre gozosos."/>
  <entry id="35509" type="1" text="17. Orad sin cesar."/>
  <entry id="35510" type="1" text="18. Dad gracias en todo; porque esta es la voluntad de Dios para con vosotros en Cristo Jesús."/>
  <entry id="35511" type="1" text="19. No apaguéis el Espíritu."/>
  <entry id="35512" type="1" text="20. No menospreciéis las profecías."/>
  <entry id="35513" type="1" text="21. Examinadlo todo; retened lo bueno."/>
  <entry id="35514" type="1" text="22. Apartaos de toda especie de mal."/>
  <entry id="35515" type="1" text="23. Y el Dios de paz os santifique en todo; para que vuestro espíritu y alma y cuerpo sea guardado entero sin reprensión para la venida de nuestro Señor Jesucristo."/>
  <entry id="35516" type="1" text="24. Fiel es el que os ha llamado; el cual también lo hará."/>
  <entry id="35517" type="1" style="subtitulo" text="Salutaciones y bendición final"/>
  <entry id="35518" type="1" text="25. Hermanos, orad por nosotros."/>
  <entry id="35519" type="1" text="26. Saludad a todos los hermanos en ósculo santo."/>
  <entry id="35520" type="1" text="27. Conjúroos por el Señor, que esta carta sea leída a todos los santos hermanos."/>
  <entry id="35521" type="1" text="28 La gracia de nuestro Señor Jesucristo sea con vosotros. Amén."/>
</page>
