{"@attributes":{"id":"340","page_number":"1","label":"1","previous":"339.xml","next":"341.xml"},"entry":[{"@attributes":{"id":"10790","type":"4","text":"(Gn. 35.22-26)"},"entry":{"@attributes":{"type":"1","tooltip":"Gn. 35.22-26","text":"22 Aconteci\u00f3 que cuando moraba Israel en aquella tierra, fue Rub\u00e9n y durmi\u00f3 con Bilha la concubina de su padre; lo cual lleg\u00f3 a saber Israel. Ahora bien, los hijos de Israel fueron doce: \r23 los hijos de Lea: Rub\u00e9n el primog\u00e9nito de Jacob; Sime\u00f3n, Lev\u00ed, Jud\u00e1, Isacar y Zabul\u00f3n. \r24 Los hijos de Raquel: Jos\u00e9 y Benjam\u00edn. \r25 Los hijos de Bilha, sierva de Raquel: Dan y Neftal\u00ed. \r26 Y los hijos de Zilpa, sierva de Lea: Gad y Aser. Estos fueron los hijos de Jacob, que le nacieron en Padan-aram.\r","width":"200","height":"200"}}},{"@attributes":{"id":"10791","type":"1","text":"1. ESTOS son los hijos de Israel: Rub\u00e9n, Sime\u00f3n, Lev\u00ed, Jud\u00e1, Issach\u00e2r, Zabul\u00f3n,"}},{"@attributes":{"id":"10792","type":"1","text":"2. Dan, Jos\u00e9, Benjam\u00edn, Nephtal\u00ed, Gad, y Aser."}},{"@attributes":{"id":"10793","type":"1","style":"subtitulo","text":"Descendientes de Jud\u00e1"}},{"@attributes":{"id":"10794","type":"1","text":"3. Los hijos de Jud\u00e1: Er, On\u00e1n, y Sela. Estos tres le nacieron de la hija de Sua, Cananea. Y Er, primog\u00e9nito de Jud\u00e1, fu\u00e9 malo delante de Jehov\u00e1; y mat\u00f3lo."}},{"@attributes":{"id":"10795","type":"1","text":"4. Y Thamar su nuera le pari\u00f3 a Phares y a Zara. Todos los hijos de Jud\u00e1 fueron cinco."}},{"@attributes":{"id":"10796","type":"1","text":"5. Los hijos de Phares: Hesr\u00f3n y Hamul."}},{"@attributes":{"id":"10797","type":"1","text":"6. Y los hijos de Zara: Zimri, Eth\u00e1n, Hem\u00e1n, y Calcol, y Darda; en todos cinco."}},{"@attributes":{"id":"10798","type":"1","text":"7. Hijo de Ch\u00e2rmi fu\u00e9 Ach\u00e2r, el que alborot\u00f3 a Israel, porque prevaric\u00f3 en el anatema."}},{"@attributes":{"id":"10799","type":"1","text":"8. Azar\u00eda fu\u00e9 hijo de Eth\u00e1n."}},{"@attributes":{"id":"10800","type":"1","text":"9. Los hijos que nacieron a Hesr\u00f3n: Jerameel, Ram, y Ch\u00ealubai."}},{"@attributes":{"id":"10801","type":"1","text":"10. Y Ram engendr\u00f3 a Aminadab; y Aminadab engendr\u00f3 a Nahas\u00f3n, pr\u00edncipe de los hijos de Jud\u00e1;"}},{"@attributes":{"id":"10802","type":"1","text":"11. Y Nahas\u00f3n engendr\u00f3 a Salma, y Salma engendr\u00f3 a Booz;"}},{"@attributes":{"id":"10803","type":"1","text":"12. Y Booz engendr\u00f3 a Obed, y Obed engendr\u00f3 a Isa\u00ed;"}},{"@attributes":{"id":"10804","type":"1","text":"13. E Isa\u00ed engendr\u00f3 a Eliab, su primog\u00e9nito, y el segundo Abinadab, y Sima el tercero;"}},{"@attributes":{"id":"10805","type":"1","text":"14. El cuarto Nathanael, el quinto Radai;"}},{"@attributes":{"id":"10806","type":"1","text":"15. El sexto Osem, el s\u00e9ptimo David:"}},{"@attributes":{"id":"10807","type":"1","text":"16. De los cuales Sarvia y Abigail fueron hermanas. Los hijos de Sarvia fueron tres: Abisai, Joab, y Asael."}},{"@attributes":{"id":"10808","type":"1","text":"17. Abigail engendr\u00f3 a Amasa, cuyo padre fu\u00e9 Jether Ismaelita."}},{"@attributes":{"id":"10809","type":"1","text":"18. Caleb hijo de Hesr\u00f3n engendr\u00f3 a Jerioth de su mujer Azuba. Y los hijos de ella fueron Jeser, Sobad, y Ard\u00f3n."}},{"@attributes":{"id":"10810","type":"1","text":"19. Y muerta Azuba, tom\u00f3 Caleb por mujer a Ephrata, la cual le pari\u00f3 a Hur."}},{"@attributes":{"id":"10811","type":"1","text":"20. Y Hur engendr\u00f3 a Uri, y Uri engendr\u00f3 a Bezaleel."}},{"@attributes":{"id":"10812","type":"1","text":"21. Despu\u00e9s entr\u00f3 Hesr\u00f3n a la hija de Mach\u00eer padre de Galaad, la cual tom\u00f3 siendo \u00e9l de sesenta a\u00f1os, y ella le pari\u00f3 a Segub."}},{"@attributes":{"id":"10813","type":"1","text":"22. Y Segub engendr\u00f3 a Jair, el cual tuvo veintitr\u00e9s ciudades en la tierra de Galaad."}},{"@attributes":{"id":"10814","type":"1","text":"23. Y Gesur y Aram tomaron las ciudades de Jair de ellos, y a Cenath con sus aldeas, sesenta lugares. Todos estos fueron de los hijos de Mach\u00eer padre de Galaad."}},{"@attributes":{"id":"10815","type":"1","text":"24. Y muerto Hesr\u00f3n en Caleb de Ephrata, Abia mujer de Hesr\u00f3n le pari\u00f3 a Ashur padre de Tecoa."}},{"@attributes":{"id":"10816","type":"1","text":"25. Y los hijos de Jerameel primog\u00e9nito de Hesr\u00f3n fueron Ram su primog\u00e9nito, Buna, Orem, Osem, y Ach\u00eea."}},{"@attributes":{"id":"10817","type":"1","text":"26. Y tuvo Jerameel otra mujer llamada Atara, que fu\u00e9 madre de Onam."}},{"@attributes":{"id":"10818","type":"1","text":"27. Y los hijos de Ram primog\u00e9nito de Jerameel fueron Maas, Jam\u00edn, y Acar."}},{"@attributes":{"id":"10819","type":"1","text":"28. Y los hijos de Onam fueron Sammai, y Jada. Los hijos de Sammai: Nadab, y Abisur."}},{"@attributes":{"id":"10820","type":"1","text":"29. Y el nombre de la mujer de Abisur fu\u00e9 Abihail, la cual le pari\u00f3 a Ab\u00e1n, y a Molib."}},{"@attributes":{"id":"10821","type":"1","text":"30. Y los hijos de Nadab: Seled y Aphaim. Y Seled muri\u00f3 sin hijos."}},{"@attributes":{"id":"10822","type":"1","text":"31. E Isi fu\u00e9 hijo fu\u00e9 hijo de Aphaim; y Sesam, hijo de Isi; \u00e9 hijo de Sesam, Alai."}},{"@attributes":{"id":"10823","type":"1","text":"32. Los hijos de Jada hermano de Simmai: Jether y Jonath\u00e1n. Y muri\u00f3 Jether sin hijos."}},{"@attributes":{"id":"10824","type":"1","text":"33. Y los hijos de Jonath\u00e1n: Peleth, y Zaza. Estos fueron los hijos de Jerameel."}},{"@attributes":{"id":"10825","type":"1","text":"34. Y Ses\u00e1n no tuvo hijos, sino hijas."}},{"@attributes":{"id":"10826","type":"1","text":"35. Y tuvo Ses\u00e1n un siervo Egipcio, llamado Jarha, al cual di\u00f3 Ses\u00e1n por mujer a su hija; y ella le pari\u00f3 a Athai."}},{"@attributes":{"id":"10827","type":"1","text":"36. Y Athai engendr\u00f3 a Nath\u00e1n, y Nath\u00e1n engendr\u00f3 a Zabad:"}},{"@attributes":{"id":"10828","type":"1","text":"37. Y Zabad engendr\u00f3 a Ephlal, y Ephlal engendr\u00f3 a Obed;"}},{"@attributes":{"id":"10829","type":"1","text":"38. Y Obed engendr\u00f3 a Jeh\u00fa, y Jeh\u00fa engendr\u00f3 a Azar\u00edas;"}},{"@attributes":{"id":"10830","type":"1","text":"39. Y Azar\u00edas engendr\u00f3 a Heles, Heles engedr\u00f3 a Elasa;"}},{"@attributes":{"id":"10831","type":"1","text":"40. Elasa engendr\u00f3 a Sismai, y Sismai engendr\u00f3 a Sallum;"}},{"@attributes":{"id":"10832","type":"1","text":"41. Y Sallum engendr\u00f3 a Jecam\u00eda, y Jecam\u00eda engendr\u00f3 a Elisama."}},{"@attributes":{"id":"10833","type":"1","text":"42. Los hijos de Caleb hermano de Jerameel fueron Mesa su primog\u00e9nito, que fu\u00e9 el padre de Ziph; y los hijos de Maresa padre de Hebr\u00f3n."}},{"@attributes":{"id":"10834","type":"1","text":"43. Y los hijos de Hebr\u00f3n: Core, y Thaphua, y Recem, y Sema."}},{"@attributes":{"id":"10835","type":"1","text":"44. Y Sema engendr\u00f3 a Raham, padre de Jorcaam; y Recem engendr\u00f3 a Sammai."}},{"@attributes":{"id":"10836","type":"1","text":"45. Ma\u00f3n fu\u00e9 hijo de Sammai, y Ma\u00f3n padre de Beth-zur."}},{"@attributes":{"id":"10837","type":"1","text":"46. Y Epha, concubina de Caleb, le pari\u00f3 a Har\u00e1n, y a Mosa, y a Gazez. Y Har\u00e1n engendr\u00f3 a Gazez."}},{"@attributes":{"id":"10838","type":"1","text":"47. Y los hijos de Joddai: Regem, Jotham, Ges\u00e1n, Pelet, Epho, y Saaph."}},{"@attributes":{"id":"10839","type":"1","text":"48. Maach\u00e2, concubina de Caleb, le pari\u00f3 a Sebet, y a Thirana."}},{"@attributes":{"id":"10840","type":"1","text":"49. Y tambi\u00e9n le pari\u00f3 a Saaph padre de Madmannah, y a Seva padre de Macbena, y padre de Ghiba. Y Achsa fu\u00e9 hija de Caleb."}},{"@attributes":{"id":"10841","type":"1","text":"50. Estos fueron los hijos de Caleb, hijo de Hur, primog\u00e9nito de Ephrata: Sobal, padre de Ch\u00eeriath-jearim;"}},{"@attributes":{"id":"10842","type":"1","text":"51. Salma, padre de Beth-lehem; Hareph, padre de Beth-gader."}},{"@attributes":{"id":"10843","type":"1","text":"52. Y los hijos de Sobal padre de Ch\u00eeriath-jearim fueron Haroeh, la mitad de los Manahethitas."}},{"@attributes":{"id":"10844","type":"1","text":"53. Y las familias de Ch\u00eeriath-jearim fueron los Ithreos, y los Phuteos, y los Samatheos, y los Misraiteos; de los cuales salieron los Soratitas, y los Estaolitas."}},{"@attributes":{"id":"10845","type":"1","text":"54. Los hijos de Salma: Beth-lehem, y los Nethophatitas, los cuales son las coronas de la casa de Joab, y de la mitad de los Manahethitas, los Soraitas."}},{"@attributes":{"id":"10846","type":"1","text":"55. Y las familias de los escribas, que moraban en Jabes, fueron los Thiratheos, Simatheos, Sucatheos; los cuales son los Cineos que vinieron de Hamath, padre de la casa de Rech\u00e2b."}}]}