<?xml version="1.0" encoding="UTF-8"?>
<page id="180" page_number="1" label="1" previous="179.xml" next="181.xml">
  <entry id="5838" type="1" text="1. Y MANDO Moisés, con los ancianos de Israel, al pueblo, diciendo: Guardaréis todos los mandamientos que yo prescribo hoy."/>
  <entry id="5839" type="1" text="2. Y será que, el día que pasareis el Jordán a la tierra que Jehová tu Dios te da, te has de levantar piedras grandes, las cuales revocarás con cal:"/>
  <entry id="5840" type="1" text="3. Y escribirás en ellas todas las palabras de esta ley, cuando hubieres pasado para entrar en la tierra que Jehová tu Dios te da, tierra que fluye leche y miel, como Jehová el Dios de tus padres te ha dicho."/>
  <entry id="5841" type="1" text="4. Será pues, cuando hubieres pasado el Jordán, que levantaréis estas piedras que yo os mando hoy, en el monte de Ebal, y las revocarás con cal:"/>
  <entry id="5842" type="1" text="5. Y edificarás allí altar a Jehová tu Dios, altar de piedras: no alzarás sobre ellas hierro."/>
  <entry id="5843" type="1" text="6. De piedras enteras edificarás el altar de Jehová tu Dios; y ofrecerás sobre él holocausto a Jehová tu Dios;"/>
  <entry id="5844" type="1" text="7. Y sacrificarás pacíficos, y comerás allí; y alegrarte has delante de Jehová tu Dios."/>
  <entry id="5845" type="1" text="8. Y escribirás en las piedras todas las palabras de esta ley muy claramente."/>
  <entry id="5846" type="1" text="9. Y Moisés, con los sacerdotes Levitas, habló a todo Israel, diciendo: Atiende y escucha, Israel: hoy eres hecho pueblo de Jehová tu Dios."/>
  <entry id="5847" type="1" text="10. Oirás pues la voz de Jehová tu Dios, y cumplirás sus mandamientos y sus estatutos, que yo te ordeno hoy."/>
  <entry id="5848" type="1" style="subtitulo" text="Las maldiciones en el monte Ebal"/>
  <entry id="5849" type="1" text="11. Y mandó Moisés al pueblo en aquel día, diciendo:"/>
  <entry id="5850" type="1" text="12. Estos estarán sobre el monte de Gerizim para bendecir al pueblo, cuando hubiereis pasado el Jordán: Simeón, y Leví, y Judá, é Issachâr, y José y Benjamín."/>
  <entry id="5851" type="1" text="13. Y estos estarán para pronunciar la maldición en el de Ebal: Rubén, Gad, y Aser, y Zabulón, Dan, y Nephtalí."/>
  <entry id="5852" type="1" text="14. Y hablarán los Levitas, y dirán a todo varón de Israel en alta voz:"/>
  <entry id="5853" type="1" text="15. Maldito el hombre que hiciere escultura ó imagen de fundición, abominación a Jehová, obra de mano de artífice, y la pusiere en oculto. Y todo el pueblo responderá y dirá: Amén."/>
  <entry id="5854" type="1" text="16. Maldito el que deshonrare a su padre ó a su madre. Y dirá todo el pueblo: Amén."/>
  <entry id="5855" type="1" text="17. Maldito el que redujere el término de su prójimo. Y dirá todo el pueblo: Amén."/>
  <entry id="5856" type="1" text="18. Maldito el que hiciere errar al ciego en el camino. Y dirá todo el pueblo: Amén."/>
  <entry id="5857" type="1" text="19. Maldito el que torciere el derecho del extranjero, del huérfano, y de la viuda. Y dirá todo el pueblo: Amén."/>
  <entry id="5858" type="1" text="20. Maldito el que se echare con la mujer de su padre; por cuanto descubrió el regazo de su padre. Y dirá todo el pueblo: Amén."/>
  <entry id="5859" type="1" text="21. Maldito el que tuviere parte con cualquiera bestia. Y dirá todo el pueblo: Amén."/>
  <entry id="5860" type="1" text="22. Maldito el que se echare con su hermana, hija de su padre, ó hija de su madre. Y dirá todo el pueblo: Amén."/>
  <entry id="5861" type="1" text="23. Maldito el que se echare con su suegra. Y dirá todo el pueblo: Amén."/>
  <entry id="5862" type="1" text="24. Maldito el que hiriere a su prójimo ocultamente. Y dirá todo el pueblo: Amén."/>
  <entry id="5863" type="1" text="25. Maldito el que recibiere don para herir de muerte al inocente. Y dirá todo el pueblo: Amén."/>
  <entry id="5864" type="1" text="26. Maldito el que no confirmare las palabras de esta ley para cumplirlas. Y dirá todo el pueblo: Amén."/>
</page>
