{"chapter":[{"@attributes":{"id":"414","number":"1","name":"Oraci\u00f3n de Nehem\u00edas sobre Jerusal\u00e9n"}},{"@attributes":{"id":"415","number":"2","name":"Artajerjes env\u00eda a Nehem\u00edas a Jerusal\u00e9n"}},{"@attributes":{"id":"416","number":"3","name":"Reparto del trabajo de reedificaci\u00f3n"}},{"@attributes":{"id":"417","number":"4","name":"Precauciones contra los enemigos"}},{"@attributes":{"id":"418","number":"5","name":"Abolici\u00f3n de la usura"}},{"@attributes":{"id":"419","number":"6","name":"Maquinaciones de los adversarios"}},{"@attributes":{"id":"420","number":"7","name":"Nehem\u00edas designa dirigentes"}},{"@attributes":{"id":"421","number":"8","name":"Esdras lee la ley al pueblo Venido el mes s\u00e9ptimo, los hijos de Israel estaban en sus ciudades;"}},{"@attributes":{"id":"422","number":"9","name":"Esdras confiesa los pecados de Israel"}},{"@attributes":{"id":"423","number":"10","name":"NEHEM\u00cdAS 10"}},{"@attributes":{"id":"424","number":"11","name":"Los habitantes de Jerusal\u00e9n"}},{"@attributes":{"id":"425","number":"12","name":"Sacerdotes y levitas"}},{"@attributes":{"id":"426","number":"13","name":"Reformas de Nehem\u00edas"}}]}