{"@attributes":{"id":"552","page_number":"1","label":"1","previous":"551.xml","next":"553.xml"},"entry":[{"@attributes":{"id":"16800","type":"1","text":"1. \u00bfHASTA cu\u00e1ndo, Jehov\u00e1? \u00bfme olvidar\u00e1s para siempre? \u00bfHasta cu\u00e1ndo esconder\u00e1s tu rostro de m\u00ed?"}},{"@attributes":{"id":"16801","type":"1","text":"2. \u00bfHasta cu\u00e1ndo pondr\u00e9 consejos en mi alma, Con ansiedad en mi coraz\u00f3n cada d\u00eda? \u00bfHasta cu\u00e1ndo ser\u00e1 enaltecido mi enemigo sobre m\u00ed?"}},{"@attributes":{"id":"16802","type":"1","text":"3. Mira, \u00f3yeme, Jehov\u00e1 Dios m\u00edo: Alumbra mis ojos, porque no duerma en muerte;"}},{"@attributes":{"id":"16803","type":"1","text":"4. Porque no diga mi enemigo, Venc\u00edlo: Mis enemigos se alegrar\u00e1n, si yo resbalare."}},{"@attributes":{"id":"16804","type":"1","text":"5. Mas yo en tu misericordia he confiado: Alegrar\u00e1se mi coraz\u00f3n en tu salud."}},{"@attributes":{"id":"16805","type":"1","text":"6. Cantar\u00e9 a Jehov\u00e1, Porque me ha hecho bien."}}]}