<?xml version="1.0" encoding="UTF-8"?>
<page id="597" page_number="1" label="1" previous="596.xml" next="598.xml">
  <entry id="17506" type="1" text="1. OH congregación, ¿pronunciáis en verdad justicia? ¿Juzgáis rectamente, hijos de los hombres?"/>
  <entry id="17507" type="1" text="2. Antes con el corazón obráis iniquidades: Hacéis pesar la violencia de vuestras manos en la tierra."/>
  <entry id="17508" type="1" text="3. Enajenáronse los impíos desde la matriz; Descarriáronse desde el vientre, hablando mentira."/>
  <entry id="17509" type="1" text="4. Veneno tienen semejante al veneno de la serpiente: Son como áspide sordo que cierra su oído;"/>
  <entry id="17510" type="1" text="5. Que no oye la voz de los que encantan, Por más hábil que el encantador sea."/>
  <entry id="17511" type="1" text="6. Oh Dios, quiebra sus dientes en sus bocas: Quiebra, oh Jehová, las muelas de los leoncillos."/>
  <entry id="17512" type="1" text="7. Corránse como aguas que se van de suyo: En entesando sus saetas, luego sean hechas pedazos."/>
  <entry id="17513" type="1" text="8. Pasen ellos como el caracol que se deslíe: Como el abortivo de mujer, no vean el sol."/>
  <entry id="17514" type="1" text="9. Antes que vuestras ollas sientan las espinas, Así vivos, así airados, los arrebatará él con tempestad."/>
  <entry id="17515" type="1" text="10. Alegraráse el justo cuando viere la venganza: Sus pies lavará en la sangre del impío."/>
  <entry id="17516" type="1" text="11. Entonces dirá el hombre: Ciertamente hay fruto para el justo; Ciertamente hay Dios que juzga en la tierra."/>
</page>
