<?xml version="1.0" encoding="UTF-8"?>
<page id="614" page_number="1" label="1" previous="613.xml" next="615.xml">
  <entry id="17798" type="1" text="1. ALABARÉMOSTE, oh Dios, alabaremos; Que cercano está tu nombre: Cuenten tus maravillas."/>
  <entry id="17799" type="1" text="2. Cuando yo tuviere tiempo, Yo juzgaré rectamente."/>
  <entry id="17800" type="1" text="3. Arruinábase la tierra y sus moradores: Yo sostengo sus columnas. (Selah.)"/>
  <entry id="17801" type="1" text="4. Dije a los insensatos: No os infatuéis; Y a los impíos: No levantéis el cuerno:"/>
  <entry id="17802" type="1" text="5. No levantéis en alto vuestro cuerno; No habléis con cerviz erguida."/>
  <entry id="17803" type="1" text="6. Porque ni de oriente, ni de occidente, Ni del desierto viene el ensalzamiento."/>
  <entry id="17804" type="1" text="7. Mas Dios es el juez: A éste abate, y a aquel ensalza."/>
  <entry id="17805" type="1" text="8. Porque el cáliz está en la mano de Jehová, y el vino es tinto, Lleno de mistura; y él derrama del mismo: Ciertamente sus heces chuparán y beberán todos los impíos de la tierra."/>
  <entry id="17806" type="1" text="9. Mas yo anunciaré siempre, Cantaré alabanzas al Dios de Jacob."/>
  <entry id="17807" type="1" text="10. Y quebraré todos los cuernos de los pecadores: Los cuernos del justo serán ensalzados."/>
</page>
