<?xml version="1.0" encoding="UTF-8"?>
<page id="622" page_number="1" label="1" previous="621.xml" next="623.xml">
  <entry id="17968" type="1" text="1. OH Dios no tengas silencio: No calles, oh Dios, ni te estés quieto."/>
  <entry id="17969" type="1" text="2. Porque he aquí que braman tus enemigos; Y tus aborrecedores han alzado cabeza."/>
  <entry id="17970" type="1" text="3. Sobre tu pueblo han consultado astuta y secretamente, Y han entrado en consejo contra tus escondidos."/>
  <entry id="17971" type="1" text="4. Han dicho: Venid, y cortémoslos de ser pueblo, Y no haya más memoria del nombre de Israel."/>
  <entry id="17972" type="1" text="5. Por esto han conspirado de corazón a una, Contra ti han hecho liga;"/>
  <entry id="17973" type="1" text="6. Los pabellones de los Idumeos y de los Ismaelitas, Moab y los Agarenos;"/>
  <entry id="17974" type="1" text="7. Gebal, y Ammón, y Amalec; Los Filisteos con los habitadores de Tiro."/>
  <entry id="17975" type="1" text="8. También el Assur se ha juntado con ellos: Son por brazo a los hijos de Lot. (Selah.)"/>
  <entry id="17976" type="1" text="9. Hazles como a Madián; Como a Sísara, como a Jabín en el arroyo de Cisón;"/>
  <entry id="17977" type="1" text="10. Que perecieron en Endor, Fueron hechos muladar de la tierra."/>
  <entry id="17978" type="1" text="11. Pon a ellos y a sus capitanes como a Oreb y como a Zeeb; Y como a Zeba y como a Zalmunna, a todos sus príncipes;"/>
  <entry id="17979" type="1" text="12. Que han dicho: Heredemos para nosotros Las moradas de Dios."/>
  <entry id="17980" type="1" text="13. Dios mío, ponlos como a torbellinos; Como a hojarascas delante del viento."/>
  <entry id="17981" type="1" text="14. Como fuego que quema el monte, Como llama que abrasa las breñas."/>
  <entry id="17982" type="1" text="15. Persíguelos así con tu tempestad, Y asómbralos con tu torbellino."/>
  <entry id="17983" type="1" text="16. Llena sus rostros de vergüenza; Y busquen tu nombre, oh Jehová."/>
  <entry id="17984" type="1" text="17. Sean afrentados y turbados para siempre; Y sean deshonrados, y perezcan."/>
  <entry id="17985" type="1" text="18. Y conozcan que tu nombre es JEHOVA; Tú solo Altísimo sobre toda la tierra."/>
</page>
