{"@attributes":{"id":"15","page_number":"1","label":"1","previous":"14.xml","next":"16.xml"},"entry":[{"@attributes":{"id":"381","type":"1","text":"1. DESPU\u00c9S de estas cosas fu\u00e9 la palabra de Jehov\u00e1 a Abram en visi\u00f3n, diciendo: No temas, Abram; yo soy tu escudo, y tu galard\u00f3n sobremanera grande."}},{"@attributes":{"id":"382","type":"1","text":"2. Y respondi\u00f3 Abram: Se\u00f1or Jehov\u00e1 \u00bfqu\u00e9 me has de dar, siendo as\u00ed que ando sin hijo, y el mayordomo de mi casa es ese Damasceno Eliezer?"}},{"@attributes":{"id":"383","type":"1","text":"3. Dijo m\u00e1s Abram: Mira que no me has dado prole, y he aqu\u00ed que es mi heredero uno nacido en mi casa."}},{"@attributes":{"id":"384","type":"1","text":"4. Y luego la palabra de Jehov\u00e1 fu\u00e9 a \u00e9l diciendo: No te heredar\u00e1 \u00e9ste, sino el que saldr\u00e1 de tus entra\u00f1as ser\u00e1 el que te herede."}},{"@attributes":{"id":"385","type":"1","text":"5. Y sac\u00f3le fuera, y dijo: Mira ahora a los cielos, y cuenta las estrellas, si las puedes contar. Y le dijo: As\u00ed ser\u00e1 tu simiente."}},{"@attributes":{"id":"386","type":"1","text":"6. Y crey\u00f3 a Jehov\u00e1, y cont\u00f3selo por justicia."}},{"@attributes":{"id":"387","type":"1","text":"7. Y d\u00edjole: Yo soy Jehov\u00e1, que te saqu\u00e9 de Ur de los Caldeos, para darte a heredar esta tierra."}},{"@attributes":{"id":"388","type":"1","text":"8. Y \u00e9l respondi\u00f3: Se\u00f1or Jehov\u00e1 \u00bfen qu\u00e9 conocer\u00e9 que la tengo de heredar?"}},{"@attributes":{"id":"389","type":"1","text":"9. Y le dijo: Ap\u00e1rtame una becerra de tres a\u00f1os, y una cabra de tres a\u00f1os, y un carnero de tres a\u00f1os, una t\u00f3rtola tambi\u00e9n, y un palomino."}},{"@attributes":{"id":"390","type":"1","text":"10. Y tom\u00f3 \u00e9l todas estas cosas, y parti\u00f3las por la mitad, y puso cada mitad una enfrente de otra; mas no parti\u00f3 las aves."}},{"@attributes":{"id":"391","type":"1","text":"11. Y descend\u00edan aves sobre los cuerpos muertos, y oje\u00e1balas Abram."}},{"@attributes":{"id":"392","type":"1","text":"12. Mas a la ca\u00edda del sol sobrecogi\u00f3 el sue\u00f1o a Abram, y he aqu\u00ed que el pavor de una grande obscuridad cay\u00f3 sobre \u00e9l."}},{"@attributes":{"id":"393","type":"1","text":"13. Entonces dijo a Abram: Ten por cierto que tu simiente ser\u00e1 peregrina en tierra no suya, y servir\u00e1 a los de all\u00ed, y ser\u00e1n por ellos afligidos cuatrocientos a\u00f1os."}},{"@attributes":{"id":"394","type":"1","text":"14. Mas tambi\u00e9n a la gente a quien servir\u00e1n, juzgar\u00e9 yo; y despu\u00e9s de esto saldr\u00e1n con grande riqueza."}},{"@attributes":{"id":"395","type":"1","text":"15. Y t\u00fa vendr\u00e1s a tus padres en paz, y ser\u00e1s sepultado en buena vejez."}},{"@attributes":{"id":"396","type":"1","text":"16. Y en la cuarta generaci\u00f3n volver\u00e1n ac\u00e1: porque aun no est\u00e1 cumplida la maldad del Amorrheo hasta aqu\u00ed."}},{"@attributes":{"id":"397","type":"1","text":"17. Y sucedi\u00f3 que puesto el sol, y ya obscurecido, dej\u00f3se ver un horno humeando, y una antorcha de fuego que pas\u00f3 por entre los animales divididos."}},{"@attributes":{"id":"398","type":"1","text":"18. En aquel d\u00eda hizo Jehov\u00e1 un pacto con Abram diciendo: A tu simiente dar\u00e9 esta tierra desde el r\u00edo de Egipto hasta el r\u00edo grande, el r\u00edo Eufrates;"}},{"@attributes":{"id":"399","type":"1","text":"19. Los Cineos, y los Ceneceos, y los Cedmoneos,"}},{"@attributes":{"id":"400","type":"1","text":"20. Y los Hetheos, y los Pherezeos, y los Raphaitas,"}},{"@attributes":{"id":"401","type":"1","text":"21. Y los Amorrheos, y los Cananeos, y los Gergeseos, y los Jebuseos."}}]}