{"@attributes":{"id":"1052","page_number":"1","label":"1","previous":"1051.xml","next":"1053.xml"},"entry":[{"@attributes":{"id":"27827","type":"1","text":"1. Y VOLVIO el \u00e1ngel que hablaba conmigo, y despert\u00f3me como un hombre que es despertado de su sue\u00f1o."}},{"@attributes":{"id":"27828","type":"1","text":"2. Y d\u00edjome: \u00bfQu\u00e9 ves? Y respond\u00ed: He mirado, y he aqu\u00ed un candelero todo de oro, con su vaso sobre su cabeza, y sus siete l\u00e1mparas encima del candelero; y siete canales para las l\u00e1mparas que est\u00e1n encima de \u00e9l;"}},{"@attributes":{"id":"27829","type":"1","text":"3. Y sobre \u00e9l dos olivas, la una a la derecha del vaso, y la otra a su izquierda."}},{"@attributes":{"id":"27830","type":"1","text":"4. Prosegu\u00ed, y habl\u00e9 a aquel \u00e1ngel que hablaba conmigo, diciendo: \u00bfQu\u00e9 es esto, se\u00f1or m\u00edo?"}},{"@attributes":{"id":"27831","type":"1","text":"5. Y el \u00e1ngel que hablaba conmigo respondi\u00f3, y d\u00edjome: \u00bfNo sabes qu\u00e9 es esto? Y dije: No, se\u00f1or m\u00edo."}},{"@attributes":{"id":"27832","type":"1","text":"6. Entonces respondi\u00f3 y habl\u00f3me, diciendo: Esta es palabra de Jehov\u00e1 a Zorobabel, en que se dice: No con ej\u00e9rcito, ni con fuerza, sino con mi esp\u00edritu, ha dicho Jehov\u00e1 de los ej\u00e9rcitos."}},{"@attributes":{"id":"27833","type":"1","text":"7. \u00bfQui\u00e9n eres t\u00fa, oh gran monte? Delante de Zorobabel ser\u00e1s reducido a llanura: \u00e9l sacar\u00e1 la primera piedra con aclamaciones de Gracia, gracia a ella."}},{"@attributes":{"id":"27834","type":"1","text":"8. Y fu\u00e9 palabra de Jehov\u00e1 a m\u00ed, diciendo:"}},{"@attributes":{"id":"27835","type":"1","text":"9. Las manos de Zorobabel echar\u00e1n el fundamento a esta casa, y sus manos la acabar\u00e1n; y conocer\u00e1s que Jehov\u00e1 de los ej\u00e9rcitos me envi\u00f3 a vosotros."}},{"@attributes":{"id":"27836","type":"1","text":"10. Porque los que menospreciaron el d\u00eda de las peque\u00f1eces se alergrar\u00e1n, y ver\u00e1n la plomada en la mano de Zorobabel. Aquellas siete son los ojos de Jehov\u00e1 que recorren por toda la tierra."}},{"@attributes":{"id":"27837","type":"1","text":"11. Habl\u00e9 m\u00e1s, y d\u00edjele: \u00bfQu\u00e9 significan estas dos olivas a la derecha del candelero, y a su izquieda?"}},{"@attributes":{"id":"27838","type":"1","text":"12. Habl\u00e9 a\u00fan de nuevo, y d\u00edjele: \u00bfQu\u00e9 significan las dos ramas de olivas que por medio de dos tubos de oro vierten de s\u00ed aceite como oro?"}},{"@attributes":{"id":"27839","type":"1","text":"13. Y respondi\u00f3me, diciendo: \u00bfNo sabes qu\u00e9 es esto? Y dije: Se\u00f1or m\u00edo, no."}},{"@attributes":{"id":"27840","type":"1","text":"14. Y \u00e9l dijo: Estos dos hijos de aceite son los que est\u00e1n delante del Se\u00f1or de toda la tierra."}}]}